mseep_singlestore_mcp_server-1.0.0.dist-info/licenses/LICENSE
src/__init__.py
src/main.py
src/version.py
src/analytics/__init__.py
src/analytics/manager.py
src/auth/__init__.py
src/auth/browser_auth.py
src/auth/callback.py
src/auth/provider.py
src/commands/__init__.py
src/commands/init.py
src/commands/start.py
src/config/__init__.py
src/config/config.py
mseep_singlestore_mcp_server-1.0.0.dist-info/METADATA
mseep_singlestore_mcp_server-1.0.0.dist-info/WHEEL
mseep_singlestore_mcp_server-1.0.0.dist-info/top_level.txt
mseep_singlestore_mcp_server-1.0.0.dist-info/RECORD
