Metadata-Version: 2.4
Name: mseep-singlestore_mcp_server
Version: 1.0.0
Summary: SingleStore MCP server
Home-page: 
Author: mseep
Author-email: support@skydeck.ai
Maintainer: mseep
Maintainer-email: support@skydeck.ai
Keywords: mseep
Classifier: Programming Language :: Python :: 3
Classifier: License :: OSI Approved :: MIT License
Classifier: Operating System :: OS Independent
Requires-Python: >=3.6
License-File: LICENSE
Requires-Dist: black>=25.1.0
Requires-Dist: flake8>=7.2.0
Requires-Dist: mcp[cli]>=1.9.4
Requires-Dist: nbformat>=5.10.4
Requires-Dist: pydantic-settings>=2.9.1
Requires-Dist: segment-analytics-python>=2.3.4
Requires-Dist: singlestoredb>=1.12.0
Requires-Dist: starlette>=0.46.2
Dynamic: author
Dynamic: author-email
Dynamic: classifier
Dynamic: description
Dynamic: description-content-type
Dynamic: keywords
Dynamic: license-file
Dynamic: maintainer
Dynamic: maintainer-email
Dynamic: requires-dist
Dynamic: requires-python
Dynamic: summary
